postgrestq/__init__.py
postgrestq/py.typed
postgrestq/task_queue.py
postgres_tq-1.2.1.dist-info/LICENSE
postgres_tq-1.2.1.dist-info/METADATA
postgres_tq-1.2.1.dist-info/WHEEL
postgres_tq-1.2.1.dist-info/top_level.txt
postgres_tq-1.2.1.dist-info/RECORD
