Metadata-Version: 2.1
Name: postgres-tq
Version: 1.2.1
Summary: Postgres Based Task Queue
Author-email: FlixTech <open-source@flixbus.com>
License: MIT
Requires-Python: >=3.9
License-File: LICENSE
Requires-Dist: psycopg[binary]>=3.1.12
Requires-Dist: psycopg-pool>=3.1.12
